README.md
setup.py
async_dataprime/__init__.py
async_dataprime/executor.py
dataframe_operator/__init__.py
dataframe_operator/dataframe_col_generator.py
dataframe_operator/dataframe_combiner.py
dataframe_operator/dataframe_driller.py
dataframe_operator/dataframe_filter.py
dataframe_operator/dataframe_sample_getter.py
dataframe_operator/dataframe_sort.py
dataframe_operator/dataframe_topN.py
dataframe_operator/operate_utils/__init__.py
dataframe_operator/operate_utils/col_generate/__init__.py
dataframe_operator/operate_utils/col_generate/base_operate.py
dataframe_operator/operate_utils/col_generate/operate_context.py
dataprime/__init__.py
dataprime/dataprime.py
dataprime/decorator.py
dataprime/init_celery.py
dataprime/params.py
dataprime.egg-info/PKG-INFO
dataprime.egg-info/SOURCES.txt
dataprime.egg-info/dependency_links.txt
dataprime.egg-info/requires.txt
dataprime.egg-info/top_level.txt
dataprime_celery/__init__.py
dataprime_celery/celery_app.py
dataprime_celery/config.py
dataprime_celery/tasks.py