Metadata-Version: 2.1
Name: dataprime
Version: 0.1.9
Summary: 数据智脑开源计算引擎dataprime
Home-page: UNKNOWN
Author: APUSIC
Author-email: 464521059@qq.com
License: Mulan PSL v2
Project-URL: Source, https://gitee.com/apusic/dataprime
Keywords: dataframe,pandas
Platform: any
